reaction_plane_fit/__init__.py
reaction_plane_fit/base.py
reaction_plane_fit/example.py
reaction_plane_fit/fit.py
reaction_plane_fit/functions.py
reaction_plane_fit/plot.py
reaction_plane_fit/py.typed
reaction_plane_fit/three_orientations.py
reaction_plane_fit/version.py
reaction_plane_fit/sample_data/__init__.py
reaction_plane_fit/sample_data/three_orientations.root
reaction_plane_fit-4.0.dist-info/LICENSE
reaction_plane_fit-4.0.dist-info/METADATA
reaction_plane_fit-4.0.dist-info/WHEEL
reaction_plane_fit-4.0.dist-info/top_level.txt
reaction_plane_fit-4.0.dist-info/RECORD
