Metadata-Version: 2.1
Name: reaction-plane-fit
Version: 4.0
Summary: Implments the reaction plane fit for background subtraction in heavy ion collisions.
Home-page: https://github.com/raymondEhlers/reactionPlaneFit
Author: Raymond Ehlers
Author-email: raymond.ehlers@cern.ch
License: BSD 3-Clause
Keywords: HEP Physics
Platform: UNKNOWN
Classifier: Development Status :: 4 - Beta
Classifier: Intended Audience :: Science/Research
Classifier: Programming Language :: Python :: 3.6
Classifier: Programming Language :: Python :: 3.7
Requires-Dist: numpy
Requires-Dist: uproot
Requires-Dist: iminuit
Requires-Dist: pachyderm (>2.2)
Requires-Dist: dataclasses ; python_version < "3.7"
Provides-Extra: dev
Requires-Dist: pre-commit ; extra == 'dev'
Requires-Dist: flake8 ; extra == 'dev'
Requires-Dist: flake8-colors ; extra == 'dev'
Requires-Dist: mypy ; extra == 'dev'
Provides-Extra: docs
Requires-Dist: sphinx ; extra == 'docs'
Requires-Dist: recommonmark ; extra == 'docs'
Requires-Dist: sphinx-markdown-tables ; extra == 'docs'
Provides-Extra: tests
Requires-Dist: pytest ; extra == 'tests'
Requires-Dist: pytest-cov ; extra == 'tests'
Requires-Dist: pytest-mock ; extra == 'tests'
Requires-Dist: codecov ; extra == 'tests'
Requires-Dist: pytest-mpl ; extra == 'tests'
